configcafe/__init__.py
configcafe/bean.py
configcafe-0.1.2.dist-info/LICENSE
configcafe-0.1.2.dist-info/WHEEL
configcafe-0.1.2.dist-info/METADATA
configcafe-0.1.2.dist-info/RECORD
